MVBLS/MVBLS.py
MVBLS/__init__.py
MVBLS/_version.py
MVBLS-1.1.dist-info/METADATA
MVBLS-1.1.dist-info/WHEEL
MVBLS-1.1.dist-info/top_level.txt
MVBLS-1.1.dist-info/RECORD
