Metadata-Version: 2.1
Name: MVBLS
Version: 1.1
Summary: Multi-view Broad Learning Systerm
Home-page: https://github.com/zhaochangming/MVBLS
Author: Chang-ming Zhao
Author-email: 1730514926@qq.com
License: UNKNOWN
Platform: UNKNOWN
Classifier: Programming Language :: Python :: 3.6
Classifier: License :: OSI Approved :: MIT License
Classifier: Operating System :: OS Independent
Requires-Python: >=3.6
